oauth_requests/__init__.py
oauth_requests/apps.py
oauth_requests/models.py
oauth_requests/oauth.py
oauth_requests/management/__init__.py
oauth_requests/management/commands/__init__.py
oauth_requests/management/commands/clear_tokens.py
oauth_requests/migrations/0001_initial.py
oauth_requests/migrations/__init__.py
django_oauth_requests-1.0.1.dist-info/LICENSE
django_oauth_requests-1.0.1.dist-info/METADATA
django_oauth_requests-1.0.1.dist-info/WHEEL
django_oauth_requests-1.0.1.dist-info/top_level.txt
django_oauth_requests-1.0.1.dist-info/RECORD
