Metadata-Version: 2.1
Name: django-oauth-requests
Version: 1.0.1
Summary: Django app for OAuth 2.0 authentication with requests
Author-email: Pavel Mises <id@dqd.cz>
Project-URL: Repository, https://github.com/dqd/django-oauth-requests
Project-URL: Issues, https://github.com/dqd/django-oauth-requests/issues
Classifier: Programming Language :: Python :: 3
Classifier: License :: OSI Approved :: MIT License
Classifier: Operating System :: OS Independent
Requires-Python: >=3.8
License-File: LICENSE
Requires-Dist: requests
Requires-Dist: django >=5.0
